<?xml version="1.0" encoding="utf-8"?>
<metadata>
	<layout title="Dettaglio utente vista selezionabile" option="com_gglms">
		<message>Dettaglio utente vista selezionabile</message>
	</layout>

	<fields name="request">
		<fieldset name="request">

			<field name="template" type="list" default="quota_sinpe_anno" label="Template pagina" description="">
				<option value="quota_sinpe_anno">SINPE - Dettaglio pagamento quote per utente</option>
				<option value="gestione_soci_sinpe">SINPE - Gestione dei soci</option>
				<option value="pagamenti_servizi_extra">SINPE - Pagamento servizi extra (es. ESPEN)</option>
				<option value="registrazione_utenti_sponsor">SINPE - Registrazione utenti reclutati sponsor</option>
				<option value="report_quiz_per_utente">GENERICO - Report quiz per utente</option>
				<option value="resend_info_corso">SKILLAB - Resetta ed invia password agli utenti per azienda e piattaforma</option>
				<option value="gestione_anagrafica_centri_sinpe">SINPE - Gestione anagrafica centri</option>
				<option value="gestione_quote_asand">ASAND - Gestione rinnovo quote</option>
				<option value="rinnovo_quota_asand">ASAND - Form rinnovo quote</option>
				<option value="gestione_accesso_utenti_aic">AIC - Gestione accesso utenti</option>
				<option value="verifica_codice_votazione">SINPE - Verifica codice votazione</option>
				<option value="votazione_candidati_sinpe">SINPE - Votazione candidati</option>
			</field>

		</fieldset>
	</fields>


</metadata>



